stream_tools/__init__.py
stream_tools/join.py
stream_tools/merge.py
stream_tools/stream.py
stream_tools/streams.py
stream_tools-0.2.0.dist-info/WHEEL
stream_tools-0.2.0.dist-info/METADATA
stream_tools-0.2.0.dist-info/RECORD
