Metadata-Version: 2.1
Name: stream-tools
Version: 0.2.0
Summary: 
Author: Mattia Terenzi
Author-email: m.terenzi92@gmail.com
Requires-Python: >=3.7,<4.0
Classifier: Programming Language :: Python :: 3
Classifier: Programming Language :: Python :: 3.7
Classifier: Programming Language :: Python :: 3.8
Classifier: Programming Language :: Python :: 3.9
Requires-Dist: aioredis (>=1.3.1,<2.0.0)
Requires-Dist: uvloop (>=0.14.0,<0.15.0)
